attenuate/__init__.py
attenuate/model.py
attenuate-0.1.1.dist-info/LICENSE.md
attenuate-0.1.1.dist-info/METADATA
attenuate-0.1.1.dist-info/WHEEL
attenuate-0.1.1.dist-info/top_level.txt
attenuate-0.1.1.dist-info/RECORD
