Metadata-Version: 2.1
Name: attenuate
Version: 0.1.1
Summary: Real-time raw speech enhancement with deep state-space modeling
Home-page: https://https://github.com/Brainchip-Inc/aTENNuate
Author: Rudy Pei
Author-email: yanrpei@gmail.com
License: Apache-2.0
Classifier: Programming Language :: Python :: 3
Classifier: License :: OSI Approved :: Apache Software License
Classifier: Operating System :: OS Independent
Requires-Python: >=3.6
License-File: LICENSE.md
Requires-Dist: pathlib
Requires-Dist: librosa
Requires-Dist: torch
Requires-Dist: torchaudio
Requires-Dist: einops
Requires-Dist: opt-einsum
Requires-Dist: huggingface-hub
